odoo/addons/stock_location_orderpoint/README.rst
odoo/addons/stock_location_orderpoint/__init__.py
odoo/addons/stock_location_orderpoint/__manifest__.py
odoo/addons/stock_location_orderpoint/data/ir_cron.xml
odoo/addons/stock_location_orderpoint/data/ir_sequence.xml
odoo/addons/stock_location_orderpoint/data/queue_job_channel.xml
odoo/addons/stock_location_orderpoint/data/queue_job_function.xml
odoo/addons/stock_location_orderpoint/demo/stock_location.xml
odoo/addons/stock_location_orderpoint/demo/stock_location_orderpoint.xml
odoo/addons/stock_location_orderpoint/demo/stock_picking_type.xml
odoo/addons/stock_location_orderpoint/demo/stock_route.xml
odoo/addons/stock_location_orderpoint/i18n/it.po
odoo/addons/stock_location_orderpoint/i18n/stock_location_orderpoint.pot
odoo/addons/stock_location_orderpoint/models/__init__.py
odoo/addons/stock_location_orderpoint/models/stock_location.py
odoo/addons/stock_location_orderpoint/models/stock_location_orderpoint.py
odoo/addons/stock_location_orderpoint/models/stock_move.py
odoo/addons/stock_location_orderpoint/models/stock_rule.py
odoo/addons/stock_location_orderpoint/readme/CONFIGURE.rst
odoo/addons/stock_location_orderpoint/readme/CONTRIBUTORS.rst
odoo/addons/stock_location_orderpoint/readme/DESCRIPTION.rst
odoo/addons/stock_location_orderpoint/security/ir.model.access.csv
odoo/addons/stock_location_orderpoint/static/description/icon.png
odoo/addons/stock_location_orderpoint/static/description/index.html
odoo/addons/stock_location_orderpoint/tests/__init__.py
odoo/addons/stock_location_orderpoint/tests/common.py
odoo/addons/stock_location_orderpoint/tests/test_location_orderpoint.py
odoo/addons/stock_location_orderpoint/views/menu.xml
odoo/addons/stock_location_orderpoint/views/stock_location.xml
odoo/addons/stock_location_orderpoint/views/stock_location_orderpoint_views.xml
odoo14_addon_stock_location_orderpoint-14.0.1.1.2.dist-info/METADATA
odoo14_addon_stock_location_orderpoint-14.0.1.1.2.dist-info/WHEEL
odoo14_addon_stock_location_orderpoint-14.0.1.1.2.dist-info/top_level.txt
odoo14_addon_stock_location_orderpoint-14.0.1.1.2.dist-info/RECORD
